Laboratorio_9/Ejercicio_003/Ejercicio_003.v
// Electrónica digital
// Valerie Valdez 19659

//                             Laboratorio #09
//                              Ejercicio 03



// Flip Flop D 1 bit

module FFD(input wire clk, EN, reset, input wire C, output reg D);
  always @ (posedge clk, posedge reset) begin

// Non-blockinf assigment
    if(reset) // Colocar todos los valores en 0
      D <= 1'b0;

    else if(EN == 1) // Enabled encendido cuenta cuenta cada flanco del reloj
      D <= C;
  end
endmodule


// Flip FLop JK

module FFJK(input wire clk, EN, reset, input wire J, K, output Q);
  wire D, QN, KN, Y1, Y2;

  not(QN, Q);
  not(KN, K);
  and(Y1, KN, Q);
  and(Y2, J, QN);
  or(D, Y1, Y2);

  FFD A1(clk, EN, reset, D, Q);

endmodule

Laboratorio_9/Ejercicio_003/Ejercicio_003_tb.v
/// Electrónica digital
// Valerie Valdez 19659

//                             Laboratorio #09
//                              Ejercicio 03


module testbench();

  // inputs
  reg clk, EN, reset;
  reg J, K;

  // Outputs
  wire Q;

  // Clock
  always
    #1 clk = ~clk;

  // Instanciar el módulo
  FFJK A1(clk, EN, reset, J, K, Q);

  initial begin
    #1
    $display("\n");
    $display("Flip Flop JK");
    $display("\n");
    $display("------------------------|-----|");
    $display(" clk  EN  reset  J   K   |  Q  |");
    $display("------------------------|-----|");
    $monitor("%b    %b    %b     %b   %b   |  %b  |", clk, EN, reset, J, K, Q);

    #1 clk = 0; reset = 1; EN = 1; J = 0; K = 0;
    #5 reset = 0; EN = 1;
    #5 J = 1;
    #5 K = 1;
    #5 J = 0;
    #5 J = 1; K = 0;

  end

    initial
      #70 $finish;

  // GTKwave para el diagrama de timing
    initial begin
      $dumpfile("Ejercicio_003_tb.vcd");
      $dumpvars(0, testbench);
    end
endmodule

Laboratorio_9/Ejercicio_003/Ejercicio_003_tb.vcd
$date
	Sat Oct 31 00:59:26 2020
$end
$version
	Icarus Verilog
$end
$timescale
	1ps
$end
$scope module testbench $end
$var wire 1 ! Q $end
$var reg 1 " EN $end
$var reg 1 # J $end
$var reg 1 $ K $end
$var reg 1 % clk $end
$var reg 1 & reset $end
$scope module A1 $end
$var wire 1 ' D $end
$var wire 1 " EN $end
$var wire 1 # J $end
$var wire 1 $ K $end
$var wire 1 ( KN $end
$var wire 1 ) QN $end
$var wire 1 * Y1 $end
$var wire 1 + Y2 $end
$var wire 1 % clk $end
$var wire 1 & reset $end
$var wire 1 ! Q $end
$scope module A1 $end
$var wire 1 ' C $end
$var wire 1 " EN $end
$var wire 1 % clk $end
$var wire 1 & reset $end
$var reg 1 ! D $end
$upscope $end
$upscope $end
$upscope $end
$enddefinitions $end
#0
$dumpvars
x+
x*
x)
x(
x'
x&
x%
x$
x#
x"
x!
$end
#2
0'
0*
1)
0!
1(
0+
0$
0#
1"
1&
0%
#3
1%
#4
0%
#5
1%
#6
0%
#7
1%
0&
#8
0%
#9
1%
#10
0%
#11
1%
#12
1'
1+
0%
1#
#13
0+
1*
0)
1!
1%
#14
0%
#15
1%
#16
0%
#17
0'
0*
0(
1%
1$
#18
0%
#19
1'
1+
1)
0!
1%
#20
0%
#21
0'
0+
0)
1!
1%
#22
0%
0#
#23
1)
0!
1%
#24
0%
#25
1%
#26
0%
#27
1'
1(
1+
1%
0$
1#
#28
0%
#29
0+
1*
0)
1!
1%
