Laboratorio_4/Problema_5/Problema_5.v
// Electrónica digital
// Laboratorio 4, problema 5
//----------------Valerie Valdez 19659-----------------------

//Tabla SOP con Gate level modeling
module TABLA_SOP_GLM(input wire A, B, C, output wire Y);

wire w1, w2, w3, w4, w5;

not(w1, B);
not(w2, C);
and(w3, A,w1,w2);
and(w4, A,B,w2);
and(w5, A,B,C);
or(Y, w3,w4,w5);

endmodule


//Tabla SOP con Behavioral modelling
module TABLA_SOP_BM(input wire A, B, C, output wire Y);

assign Y = (A & ~B & ~C) | (A & B & ~C) | (A & B & C);

endmodule


//Tabla POS con Gate Level modeling
module TABLA_POS_GLM(input wire A,B,C, output wire Y);

wire q1, q2, q3, q4, q5, q6, q7, q8;

not(q1, A);
not(q2, B);
not(q3, C);
or(q4, A,B,C);
or(q5, A,B,q3);
or(q6, A,q2,C);
or(q7, A,q2,q3);
or(q8, q1,B,q3);
and(Y, q4,q5,q6,q7,q8);

endmodule


//Tabla POS con Behavioral Modelling
module TABLA_POS_BM(input wire A,B,C, output wire Y);

assign Y = (A | B | C) & (A | B | ~C) & (A | ~B | C) & (A | ~B | ~C) & (~A | B | ~C);

endmodule


// Tabla ecuación minimizada con Gate Level Modeling
module TABLA_MIN_GLM(input wire A,B,C, output wire Y);

wire s1, s2, s3;

not(s1, C);
and(s2, A,s1);
and(s3, A,B);
or(Y, s2,s3);

endmodule


// Tabla ecuación minimizada con Behavioral Modeling
module TABLA_MIN_BM(input wire A,B,C, output wire Y);

assign Y = (A & ~C) | (A & B);

endmodule

Laboratorio_4/Problema_5/Problema_5_tb.v
// Electrónica digital
// Laboratorio 4
// Problema 5
// ------------------------Valerie Valdez 19659------------------------

module problema_5_tb();

// TABLA_SOP_GLM
reg a1, a2, a3;
wire led1;

TABLA_SOP_GLM G1(a1,a2,a3, led1);

initial begin
  $display("\n");
  $display("TABLA SOP");
  $display("\n");
  $display("A B C | Y");
  $display("------|---");
  $monitor("%b %b %b | %b", a1,a2,a3, led1);

  a1 = 0; a2 = 0; a3 = 0;
  #1 a1 = 0; a2 = 0; a3 = 1;
  #1 a1 = 0; a2 = 1; a3 = 0;
  #1 a1 = 0; a2 = 1; a3 = 1;
  #1 a1 = 1; a2 = 0; a3 = 0;
  #1 a1 = 1; a2 = 0; a3 = 1;
  #1 a1 = 1; a2 = 1; a3 = 0;
  #1 a1 = 1; a2 = 1; a3 = 1;

  end


// Tabla_SOP_BM
reg b1, b2, b3;
wire led2;

  TABLA_SOP_BM G2(b1,b2,b3, led2);

  initial begin
    #9
    $display("\n");
    $display("A B C | Y");
    $display("------|---");
    $monitor("%b %b %b | %b", b1,b2,b3, led2);

    b1 = 0; b2 = 0; b3 = 0;
    #1 b1 = 0; b2 = 0; b3 = 1;
    #1 b1 = 0; b2 = 1; b3 = 0;
    #1 b1 = 0; b2 = 1; b3 = 1;
    #1 b1 = 1; b2 = 0; b3 = 0;
    #1 b1 = 1; b2 = 0; b3 = 1;
    #1 b1 = 1; b2 = 1; b3 = 0;
    #1 b1 = 1; b2 = 1; b3 = 1;

  end


//Tabla Pos con Gate Level modeling
reg c1, c2, c3;
wire led3;

  TABLA_POS_GLM G3(c1,c2,c3, led3);

  initial begin
    #17
    $display("\n");
    $display("TABLA POS");
    $display("\n");
    $display("A B C | Y");
    $display("------|---");
    $monitor("%b %b %b | %b", c1,c2,c3, led3);

    c1 = 0; c2 = 0; c3 = 0;
    #1 c1 = 0; c2 = 0; c3 = 1;
    #1 c1 = 0; c2 = 1; c3 = 0;
    #1 c1 = 0; c2 = 1; c3 = 1;
    #1 c1 = 1; c2 = 0; c3 = 0;
    #1 c1 = 1; c2 = 0; c3 = 1;
    #1 c1 = 1; c2 = 1; c3 = 0;
    #1 c1 = 1; c2 = 1; c3 = 1;

end


//Tabla Pos con Behavioral Modelling
reg d1, d2, d3;
wire led4;

  TABLA_POS_BM G4(d1,d2,d3, led4);

  initial begin
    #25
    $display("\n");
    $display("A B C | Y");
    $display("------|---");
    $monitor("%b %b %b | %b", d1,d2,d3, led4);

    d1 = 0; d2 = 0; d3 = 0;
    #1 d1 = 0; d2 = 0; d3 = 1;
    #1 d1 = 0; d2 = 1; d3 = 0;
    #1 d1 = 0; d2 = 1; d3 = 1;
    #1 d1 = 1; d2 = 0; d3 = 0;
    #1 d1 = 1; d2 = 0; d3 = 1;
    #1 d1 = 1; d2 = 1; d3 = 0;
    #1 d1 = 1; d2 = 1; d3 = 1;

    end


// Tabla ecuación minimizada con Gate Level modeling
reg e1, e2, e3;
wire led5;

  TABLA_MIN_GLM G5(e1,e2,e3, led5);

  initial begin
    #33
    $display("\n");
    $display("Tabla: ecuacion minimizada");
    $display("\n");
    $display("A B C | Y");
    $display("------|---");
    $monitor("%b %b %b | %b", e1,e2,e3, led5);

    e1 = 0; e2 = 0; e3 = 0;
    #1 e1 = 0; e2 = 0; e3 = 1;
    #1 e1 = 0; e2 = 1; e3 = 0;
    #1 e1 = 0; e2 = 1; e3 = 1;
    #1 e1 = 1; e2 = 0; e3 = 0;
    #1 e1 = 1; e2 = 0; e3 = 1;
    #1 e1 = 1; e2 = 1; e3 = 0;
    #1 e1 = 1; e2 = 1; e3 = 1;

    end


// Tabla ecuación minimizada con Behavioral Modeling
reg f1, f2, f3;
wire led6;

  TABLA_MIN_BM G6(f1,f2,f3, led6);

  initial begin
    #41
    $display("\n");
    $display("A B C | Y");
    $display("------|---");
    $monitor("%b %b %b | %b", f1,f2,f3, led6);

    f1 = 0; f2 = 0; f3 = 0;
    #1 f1 = 0; f2 = 0; f3 = 1;
    #1 f1 = 0; f2 = 1; f3 = 0;
    #1 f1 = 0; f2 = 1; f3 = 1;
    #1 f1 = 1; f2 = 0; f3 = 0;
    #1 f1 = 1; f2 = 0; f3 = 1;
    #1 f1 = 1; f2 = 1; f3 = 0;
    #1 f1 = 1; f2 = 1; f3 = 1;

    end

    initial
      #49 $finish;

      initial begin
        $dumpfile("Problema_5_tb.vcd");
        $dumpvars(0, problema_5_tb);
        end

  endmodule

Laboratorio_4/Problema_5/Problema_5_tb.vcd
$date
	Sun Aug 09 06:25:40 2020
$end
$version
	Icarus Verilog
$end
$timescale
	1ps
$end
$scope module problema_5_tb $end
$var wire 1 ! led6 $end
$var wire 1 " led5 $end
$var wire 1 # led4 $end
$var wire 1 $ led3 $end
$var wire 1 % led2 $end
$var wire 1 & led1 $end
$var reg 1 ' a1 $end
$var reg 1 ( a2 $end
$var reg 1 ) a3 $end
$var reg 1 * b1 $end
$var reg 1 + b2 $end
$var reg 1 , b3 $end
$var reg 1 - c1 $end
$var reg 1 . c2 $end
$var reg 1 / c3 $end
$var reg 1 0 d1 $end
$var reg 1 1 d2 $end
$var reg 1 2 d3 $end
$var reg 1 3 e1 $end
$var reg 1 4 e2 $end
$var reg 1 5 e3 $end
$var reg 1 6 f1 $end
$var reg 1 7 f2 $end
$var reg 1 8 f3 $end
$scope module G1 $end
$var wire 1 ' A $end
$var wire 1 ( B $end
$var wire 1 ) C $end
$var wire 1 & Y $end
$var wire 1 9 w1 $end
$var wire 1 : w2 $end
$var wire 1 ; w3 $end
$var wire 1 < w4 $end
$var wire 1 = w5 $end
$upscope $end
$scope module G2 $end
$var wire 1 * A $end
$var wire 1 + B $end
$var wire 1 , C $end
$var wire 1 % Y $end
$upscope $end
$scope module G3 $end
$var wire 1 - A $end
$var wire 1 . B $end
$var wire 1 / C $end
$var wire 1 $ Y $end
$var wire 1 > q1 $end
$var wire 1 ? q2 $end
$var wire 1 @ q3 $end
$var wire 1 A q4 $end
$var wire 1 B q5 $end
$var wire 1 C q6 $end
$var wire 1 D q7 $end
$var wire 1 E q8 $end
$upscope $end
$scope module G4 $end
$var wire 1 0 A $end
$var wire 1 1 B $end
$var wire 1 2 C $end
$var wire 1 # Y $end
$upscope $end
$scope module G5 $end
$var wire 1 3 A $end
$var wire 1 4 B $end
$var wire 1 5 C $end
$var wire 1 " Y $end
$var wire 1 F s1 $end
$var wire 1 G s2 $end
$var wire 1 H s3 $end
$upscope $end
$scope module G6 $end
$var wire 1 6 A $end
$var wire 1 7 B $end
$var wire 1 8 C $end
$var wire 1 ! Y $end
$upscope $end
$upscope $end
$enddefinitions $end
#0
$dumpvars
xH
xG
xF
xE
xD
xC
xB
xA
x@
x?
x>
0=
0<
0;
1:
19
x8
x7
x6
x5
x4
x3
x2
x1
x0
x/
x.
x-
x,
x+
x*
0)
0(
0'
0&
x%
x$
x#
x"
x!
$end
#1
0:
1)
#2
1:
09
0)
1(
#3
0:
1)
#4
1&
1;
1:
19
0)
0(
1'
#5
0&
0;
0:
1)
#6
1&
1<
1:
09
0)
1(
#7
0<
0:
1=
1)
#9
0%
0,
0+
0*
#10
1,
#11
0,
1+
#12
1,
#13
1%
0,
0+
1*
#14
0%
1,
#15
1%
0,
1+
#16
1,
#17
0$
1B
1C
1D
1@
1?
1E
1>
0A
0/
0.
0-
#18
0$
0B
0@
1A
1/
#19
1@
0C
0?
1B
0/
1.
#20
0$
0D
0@
1C
1/
#21
1$
1@
1?
1E
0>
1D
0/
0.
1-
#22
0$
0E
0@
1/
#23
1$
1@
0?
1E
0/
1.
#24
0@
1/
#25
0#
02
01
00
#26
12
#27
02
11
#28
12
#29
1#
02
01
10
#30
0#
12
#31
1#
02
11
#32
12
#33
0"
1F
0G
0H
05
04
03
#34
0F
15
#35
1F
05
14
#36
0F
15
#37
1"
1G
1F
05
04
13
#38
0"
0G
0F
15
#39
1G
1"
1F
1H
05
14
#40
0G
0F
15
#41
0!
08
07
06
#42
18
#43
08
17
#44
18
#45
1!
08
07
16
#46
0!
18
#47
1!
08
17
#48
18
