Laboratorio_8/Contador/Contador.v
// Universidad del Valle de Guatemala
// Valerie Valdez

//                         Electrónica digital
//                            Laboratorio 8


// Implementar un contador de 12 bits con un enable y capaz de hacer un load

module contador(input wire clk, rst, en, blo,
  input wire [11:0]load,
  output reg [11:0]val);

// Non-blocking assigment
    always @(posedge clk or posedge rst or posedge blo) begin

      if(rst == 1) // Colocar todos los valores en 0
        val <= 12'b000000000000;

      else if(en == 1) //Enabled encendido cuenta en cada flanco de reloj
        val <= val + 1;

      else if(blo == 1) // Blo encendido entonces Load comienza a contar
        val <= load;

        end
endmodule

Laboratorio_8/Contador/Contador_tb.v
// Universidad del Valle de Guatemala
// Valerie Valdez

//                         Electrónica digital
//                            Laboratorio 8
//                          Testbench contador

//Declarar el módulo
module testbench();
  reg clk, rst, en, blo;
  reg [11:0]load;
  wire [11:0]val;

//Llamar al módulo
contador A1(clk, rst, en, blo, load, val);

initial begin
#1
$display("\n");
$display(" Contador de 12 bits ");
$display("\n");
$display("|-------------------------|--------------|");
$display("|clk  rst  en  blo  load  |     val      |");
$display("|-------------------------|--------------|");
$monitor("|%b  %b  %b  %b  %b | %b |", clk, rst, en, blo, load, val);


clk = 0; rst = 0; en = 0; blo = 0; load = 12'b000000000000;
#1 rst = 0;
#1 rst = 0;
#1 rst = 1;
#1 rst = 0;
#2 blo = 1; load = 12'b000001000010;
#1 blo = 0; en = 1;
#1 en = 1;

end

always
#1 clk = ~clk;

initial
#200 $finish;

//Gtk wave
initial begin
  $dumpfile("Contador_tb.vcd");
  $dumpvars(0, testbench);
end
endmodule

Laboratorio_8/Contador/Contador_tb.vcd
$date
	Fri Oct 23 11:47:09 2020
$end
$version
	Icarus Verilog
$end
$timescale
	1ps
$end
$scope module testbench $end
$var wire 12 ! val [11:0] $end
$var reg 1 " blo $end
$var reg 1 # clk $end
$var reg 1 $ en $end
$var reg 12 % load [11:0] $end
$var reg 1 & rst $end
$scope module A1 $end
$var wire 1 " blo $end
$var wire 1 # clk $end
$var wire 1 $ en $end
$var wire 12 ' load [11:0] $end
$var wire 1 & rst $end
$var reg 12 ( val [11:0] $end
$upscope $end
$upscope $end
$enddefinitions $end
#0
$dumpvars
bx (
bx '
x&
bx %
x$
x#
x"
bx !
$end
#1
b0 %
b0 '
0"
0$
0&
1#
#2
0#
#3
1#
#4
b0 !
b0 (
0#
1&
#5
1#
0&
#6
0#
#7
b1000010 !
b1000010 (
1#
b1000010 %
b1000010 '
1"
#8
0#
1$
0"
#9
b1000011 !
b1000011 (
1#
#10
0#
#11
b1000100 !
b1000100 (
1#
#12
0#
#13
b1000101 !
b1000101 (
1#
#14
0#
#15
b1000110 !
b1000110 (
1#
#16
0#
#17
b1000111 !
b1000111 (
1#
#18
0#
#19
b1001000 !
b1001000 (
1#
#20
0#
#21
b1001001 !
b1001001 (
1#
#22
0#
#23
b1001010 !
b1001010 (
1#
#24
0#
#25
b1001011 !
b1001011 (
1#
#26
0#
#27
b1001100 !
b1001100 (
1#
#28
0#
#29
b1001101 !
b1001101 (
1#
#30
0#
#31
b1001110 !
b1001110 (
1#
#32
0#
#33
b1001111 !
b1001111 (
1#
#34
0#
#35
b1010000 !
b1010000 (
1#
#36
0#
#37
b1010001 !
b1010001 (
1#
#38
0#
#39
b1010010 !
b1010010 (
1#
#40
0#
#41
b1010011 !
b1010011 (
1#
#42
0#
#43
b1010100 !
b1010100 (
1#
#44
0#
#45
b1010101 !
b1010101 (
1#
#46
0#
#47
b1010110 !
b1010110 (
1#
#48
0#
#49
b1010111 !
b1010111 (
1#
#50
0#
#51
b1011000 !
b1011000 (
1#
#52
0#
#53
b1011001 !
b1011001 (
1#
#54
0#
#55
b1011010 !
b1011010 (
1#
#56
0#
#57
b1011011 !
b1011011 (
1#
#58
0#
#59
b1011100 !
b1011100 (
1#
#60
0#
#61
b1011101 !
b1011101 (
1#
#62
0#
#63
b1011110 !
b1011110 (
1#
#64
0#
#65
b1011111 !
b1011111 (
1#
#66
0#
#67
b1100000 !
b1100000 (
1#
#68
0#
#69
b1100001 !
b1100001 (
1#
#70
0#
#71
b1100010 !
b1100010 (
1#
#72
0#
#73
b1100011 !
b1100011 (
1#
#74
0#
#75
b1100100 !
b1100100 (
1#
#76
0#
#77
b1100101 !
b1100101 (
1#
#78
0#
#79
b1100110 !
b1100110 (
1#
#80
0#
#81
b1100111 !
b1100111 (
1#
#82
0#
#83
b1101000 !
b1101000 (
1#
#84
0#
#85
b1101001 !
b1101001 (
1#
#86
0#
#87
b1101010 !
b1101010 (
1#
#88
0#
#89
b1101011 !
b1101011 (
1#
#90
0#
#91
b1101100 !
b1101100 (
1#
#92
0#
#93
b1101101 !
b1101101 (
1#
#94
0#
#95
b1101110 !
b1101110 (
1#
#96
0#
#97
b1101111 !
b1101111 (
1#
#98
0#
#99
b1110000 !
b1110000 (
1#
#100
0#
#101
b1110001 !
b1110001 (
1#
#102
0#
#103
b1110010 !
b1110010 (
1#
#104
0#
#105
b1110011 !
b1110011 (
1#
#106
0#
#107
b1110100 !
b1110100 (
1#
#108
0#
#109
b1110101 !
b1110101 (
1#
#110
0#
#111
b1110110 !
b1110110 (
1#
#112
0#
#113
b1110111 !
b1110111 (
1#
#114
0#
#115
b1111000 !
b1111000 (
1#
#116
0#
#117
b1111001 !
b1111001 (
1#
#118
0#
#119
b1111010 !
b1111010 (
1#
#120
0#
#121
b1111011 !
b1111011 (
1#
#122
0#
#123
b1111100 !
b1111100 (
1#
#124
0#
#125
b1111101 !
b1111101 (
1#
#126
0#
#127
b1111110 !
b1111110 (
1#
#128
0#
#129
b1111111 !
b1111111 (
1#
#130
0#
#131
b10000000 !
b10000000 (
1#
#132
0#
#133
b10000001 !
b10000001 (
1#
#134
0#
#135
b10000010 !
b10000010 (
1#
#136
0#
#137
b10000011 !
b10000011 (
1#
#138
0#
#139
b10000100 !
b10000100 (
1#
#140
0#
#141
b10000101 !
b10000101 (
1#
#142
0#
#143
b10000110 !
b10000110 (
1#
#144
0#
#145
b10000111 !
b10000111 (
1#
#146
0#
#147
b10001000 !
b10001000 (
1#
#148
0#
#149
b10001001 !
b10001001 (
1#
#150
0#
#151
b10001010 !
b10001010 (
1#
#152
0#
#153
b10001011 !
b10001011 (
1#
#154
0#
#155
b10001100 !
b10001100 (
1#
#156
0#
#157
b10001101 !
b10001101 (
1#
#158
0#
#159
b10001110 !
b10001110 (
1#
#160
0#
#161
b10001111 !
b10001111 (
1#
#162
0#
#163
b10010000 !
b10010000 (
1#
#164
0#
#165
b10010001 !
b10010001 (
1#
#166
0#
#167
b10010010 !
b10010010 (
1#
#168
0#
#169
b10010011 !
b10010011 (
1#
#170
0#
#171
b10010100 !
b10010100 (
1#
#172
0#
#173
b10010101 !
b10010101 (
1#
#174
0#
#175
b10010110 !
b10010110 (
1#
#176
0#
#177
b10010111 !
b10010111 (
1#
#178
0#
#179
b10011000 !
b10011000 (
1#
#180
0#
#181
b10011001 !
b10011001 (
1#
#182
0#
#183
b10011010 !
b10011010 (
1#
#184
0#
#185
b10011011 !
b10011011 (
1#
#186
0#
#187
b10011100 !
b10011100 (
1#
#188
0#
#189
b10011101 !
b10011101 (
1#
#190
0#
#191
b10011110 !
b10011110 (
1#
#192
0#
#193
b10011111 !
b10011111 (
1#
#194
0#
#195
b10100000 !
b10100000 (
1#
#196
0#
#197
b10100001 !
b10100001 (
1#
#198
0#
#199
b10100010 !
b10100010 (
1#
