Laboratorio_5/Lab_5.v
// Electrónica digital
// Laboratorio #5
// --------------------------Valerie Valdez 19659-------------------------------

// Muxes de uso general

// Mux 2:1
module MUX2_1(input wire S, D0, D1, output wire Y); //Generar y nombrar el módulo
    assign Y = S? D1 : D0; // Cuando S es = 0, toma el valor menos significativo. Cuando S es = 1, toma el valor más significativo

endmodule


// Mux 4:1
module MUX4_1(input wire D0, D1, D2, D3, input wire [1:0]S1, output wire Y);

  wire Y1, Y2;

  MUX2_1 m1(S1[0], D0, D1, Y1);
  MUX2_1 m2(S1[0], D2, D3, Y2);
  MUX2_1 m3(S1[1], Y1, Y2, Y);

endmodule


// Mux 8:1
module MUX8_1(input wire D0, D1, D2, D3, D4, D5, D6, D7, input wire [2:0]S1, output wire Y);

  wire Y1, Y2;

  MUX4_1 m1(D0, D1, D2, D3, S1[1:0], Y1);
  MUX4_1 m2(D4, D5, D6, D7, S1[1:0], Y2);
  MUX2_1 m3(S1[2], Y1, Y2, Y);

endmodule



// Tabla de verdad con MUX 2:1
module TABLA_1_MUX2(input wire A, B, C, output wire Y);

  assign Y1 = (B ^ C);
  assign Y2 = ~(B ^ C);
  MUX2_1 m1(A, Y1, Y2, Y);

endmodule


// Tabla de verdad con MUX 4:1

module TABLA_1_MUX4(input wire A, B, C, output wire Y);

  wire Y1;
  assign Y1 = ~C;
  wire [1:0]S1;
  assign S1[0] = B;
  assign S1[1] = A;
  MUX4_1 m1(C, ~C, ~C, C, S1[1:0], Y);

endmodule


// Tabla de verdad con MUX 8:1
module TABLA_1_MUX8(input wire A, B, C, V, G, output wire Y);

  wire [2:0]S1;
  assign S1[0] = C;
  assign S1[1] = B;
  assign S1[2] = A;
  MUX8_1 m1(G, V, V, G, V, G, G, V, S1[2:0], Y);

endmodule


// Tabla de verdad 2 con MUX 2:1
module TABLA_2_MUX2(input wire A, B, C, output wire Y);

  assign Y1 = (B ~| C);
  assign Y2 = ~(B & C);
  MUX2_1 m1(A, Y1, Y2, Y);

endmodule


// Tabla de verdad 2 con MUX 4:1
module TABLA_2_MUX4(input wire A, B, C, V, G, output wire Y);

  wire [1:0]S1;
  assign S1[0] = B;
  assign S1[1] = A;
  MUX4_1 m1(~C, G, V, ~C, S1[1:0], Y);

endmodule


// Tabla de verdad 2 con MUX 8:1
module TABLA_2_MUX8(input wire A, B, C, V, G, output wire Y);

  wire[2:0]S1;
  assign S1[0] = C;
  assign S1[1] = B;
  assign S1[2] = A;
  MUX8_1 m1(V, G, G, G, V, V, V, G, S1[2:0], Y);

endmodule

Laboratorio_5/Lab_5_tb.v
// Electrónica digital
// Laboratorio 5
//----------------------------Valerie Valdez------------------------------------

module testbench();

reg v1, v2, v3;
wire led1, led2, led3, led4, led5, led6;
wire V;
wire G;
assign V = 1;
assign G = 0;

TABLA_1_MUX2 G1(v1,v2,v3, led1);
TABLA_1_MUX4 G2(v1,v2,v3, led2);
TABLA_1_MUX8 G3(v1,v2,v3,V,G, led3);
TABLA_2_MUX2 G4(v1,v2,v3, led4);
TABLA_2_MUX4 G5(v1,v2,v3,V,G, led5);
TABLA_2_MUX8 G6(v1,v2,v3,V,G, led6);

initial begin
  $display("\n");
  $display("TABLA 1, MUX 2:1");
  $display("\n");
  $display("A B C | Y");
  $display("------|--");
  $monitor("%b %b %b | %b", v1,v2,v3, led1);

      v1 = 0; v2 = 0; v3 = 0;
      #1 v1 = 0; v2 = 0; v3 = 1;
      #1 v1 = 0; v2 = 1; v3 = 0;
      #1 v1 = 0; v2 = 1; v3 = 1;
      #1 v1 = 1; v2 = 0; v3 = 0;
      #1 v1 = 1; v2 = 0; v3 = 1;
      #1 v1 = 1; v2 = 1; v3 = 0;
      #1 v1 = 1; v2 = 1; v3 = 1;

end


initial begin
  #8
  $display("\n");
  $display("TABLA 1, MUX 4:1");
  $display("\n");
  $display("A B C | Y");
  $display("------|--");
  $monitor("%b %b %b | %b", v1,v2,v3, led2);

      v1 = 0; v2 = 0; v3 = 0;
      #1 v1 = 0; v2 = 0; v3 = 1;
      #1 v1 = 0; v2 = 1; v3 = 0;
      #1 v1 = 0; v2 = 1; v3 = 1;
      #1 v1 = 1; v2 = 0; v3 = 0;
      #1 v1 = 1; v2 = 0; v3 = 1;
      #1 v1 = 1; v2 = 1; v3 = 0;
      #1 v1 = 1; v2 = 1; v3 = 1;

end


initial begin
  #16
  $display("\n");
  $display("TABLA 1, MUX 8:1");
  $display("\n");
  $display("A B C | Y");
  $display("------|--");
  $monitor("%b %b %b | %b", v1,v2,v3, led3);

      v1 = 0; v2 = 0; v3 = 0;
      #1 v1 = 0; v2 = 0; v3 = 1;
      #1 v1 = 0; v2 = 1; v3 = 0;
      #1 v1 = 0; v2 = 1; v3 = 1;
      #1 v1 = 1; v2 = 0; v3 = 0;
      #1 v1 = 1; v2 = 0; v3 = 1;
      #1 v1 = 1; v2 = 1; v3 = 0;
      #1 v1 = 1; v2 = 1; v3 = 1;

end



initial begin
  #24
  $display("\n");
  $display("TABLA 2, MUX 2:1");
  $display("\n");
  $display("A B C | Y");
  $display("------|--");
  $monitor("%b %b %b | %b", v1,v2,v3, led4);

      v1 = 0; v2 = 0; v3 = 0;
      #1 v1 = 0; v2 = 0; v3 = 1;
      #1 v1 = 0; v2 = 1; v3 = 0;
      #1 v1 = 0; v2 = 1; v3 = 1;
      #1 v1 = 1; v2 = 0; v3 = 0;
      #1 v1 = 1; v2 = 0; v3 = 1;
      #1 v1 = 1; v2 = 1; v3 = 0;
      #1 v1 = 1; v2 = 1; v3 = 1;

end


initial begin
  #32
  $display("\n");
  $display("TABLA 2, MUX 4:1");
  $display("\n");
  $display("A B C | Y");
  $display("------|--");
  $monitor("%b %b %b | %b", v1,v2,v3, led5);

      v1 = 0; v2 = 0; v3 = 0;
      #1 v1 = 0; v2 = 0; v3 = 1;
      #1 v1 = 0; v2 = 1; v3 = 0;
      #1 v1 = 0; v2 = 1; v3 = 1;
      #1 v1 = 1; v2 = 0; v3 = 0;
      #1 v1 = 1; v2 = 0; v3 = 1;
      #1 v1 = 1; v2 = 1; v3 = 0;
      #1 v1 = 1; v2 = 1; v3 = 1;

end


initial begin
  #40
  $display("\n");
  $display("TABLA 2, MUX 8:1");
  $display("\n");
  $display("A B C | Y");
  $display("------|--");
  $monitor("%b %b %b | %b", v1,v2,v3, led6);

      v1 = 0; v2 = 0; v3 = 0;
      #1 v1 = 0; v2 = 0; v3 = 1;
      #1 v1 = 0; v2 = 1; v3 = 0;
      #1 v1 = 0; v2 = 1; v3 = 1;
      #1 v1 = 1; v2 = 0; v3 = 0;
      #1 v1 = 1; v2 = 0; v3 = 1;
      #1 v1 = 1; v2 = 1; v3 = 0;
      #1 v1 = 1; v2 = 1; v3 = 1;

end



initial
  #71 $finish;

initial begin
  $dumpfile("Lab_5_tb.vcd");
  $dumpvars(0, testbench);
end

endmodule

Laboratorio_5/Lab_5_tb.vcd
$date
	Sat Aug 15 22:42:59 2020
$end
$version
	Icarus Verilog
$end
$timescale
	1ps
$end
$scope module testbench $end
$var wire 1 ! G $end
$var wire 1 " V $end
$var wire 1 # led6 $end
$var wire 1 $ led5 $end
$var wire 1 % led4 $end
$var wire 1 & led3 $end
$var wire 1 ' led2 $end
$var wire 1 ( led1 $end
$var reg 1 ) v1 $end
$var reg 1 * v2 $end
$var reg 1 + v3 $end
$scope module G1 $end
$var wire 1 ) A $end
$var wire 1 * B $end
$var wire 1 + C $end
$var wire 1 , Y1 $end
$var wire 1 - Y2 $end
$var wire 1 ( Y $end
$scope module m1 $end
$var wire 1 , D0 $end
$var wire 1 - D1 $end
$var wire 1 ) S $end
$var wire 1 ( Y $end
$upscope $end
$upscope $end
$scope module G2 $end
$var wire 1 ) A $end
$var wire 1 * B $end
$var wire 1 + C $end
$var wire 1 . Y1 $end
$var wire 1 ' Y $end
$var wire 2 / S1 [1:0] $end
$scope module m1 $end
$var wire 1 + D0 $end
$var wire 1 0 D1 $end
$var wire 1 1 D2 $end
$var wire 1 + D3 $end
$var wire 2 2 S1 [1:0] $end
$var wire 1 3 Y2 $end
$var wire 1 4 Y1 $end
$var wire 1 ' Y $end
$scope module m1 $end
$var wire 1 + D0 $end
$var wire 1 0 D1 $end
$var wire 1 5 S $end
$var wire 1 4 Y $end
$upscope $end
$scope module m2 $end
$var wire 1 1 D0 $end
$var wire 1 + D1 $end
$var wire 1 6 S $end
$var wire 1 3 Y $end
$upscope $end
$scope module m3 $end
$var wire 1 4 D0 $end
$var wire 1 3 D1 $end
$var wire 1 7 S $end
$var wire 1 ' Y $end
$upscope $end
$upscope $end
$upscope $end
$scope module G3 $end
$var wire 1 ) A $end
$var wire 1 * B $end
$var wire 1 + C $end
$var wire 1 ! G $end
$var wire 1 " V $end
$var wire 1 & Y $end
$var wire 3 8 S1 [2:0] $end
$scope module m1 $end
$var wire 1 ! D0 $end
$var wire 1 " D1 $end
$var wire 1 " D2 $end
$var wire 1 ! D3 $end
$var wire 1 " D4 $end
$var wire 1 ! D5 $end
$var wire 1 ! D6 $end
$var wire 1 " D7 $end
$var wire 3 9 S1 [2:0] $end
$var wire 1 : Y2 $end
$var wire 1 ; Y1 $end
$var wire 1 & Y $end
$scope module m1 $end
$var wire 1 ! D0 $end
$var wire 1 " D1 $end
$var wire 1 " D2 $end
$var wire 1 ! D3 $end
$var wire 2 < S1 [1:0] $end
$var wire 1 = Y2 $end
$var wire 1 > Y1 $end
$var wire 1 ; Y $end
$scope module m1 $end
$var wire 1 ! D0 $end
$var wire 1 " D1 $end
$var wire 1 ? S $end
$var wire 1 > Y $end
$upscope $end
$scope module m2 $end
$var wire 1 " D0 $end
$var wire 1 ! D1 $end
$var wire 1 @ S $end
$var wire 1 = Y $end
$upscope $end
$scope module m3 $end
$var wire 1 > D0 $end
$var wire 1 = D1 $end
$var wire 1 A S $end
$var wire 1 ; Y $end
$upscope $end
$upscope $end
$scope module m2 $end
$var wire 1 " D0 $end
$var wire 1 ! D1 $end
$var wire 1 ! D2 $end
$var wire 1 " D3 $end
$var wire 2 B S1 [1:0] $end
$var wire 1 C Y2 $end
$var wire 1 D Y1 $end
$var wire 1 : Y $end
$scope module m1 $end
$var wire 1 " D0 $end
$var wire 1 ! D1 $end
$var wire 1 E S $end
$var wire 1 D Y $end
$upscope $end
$scope module m2 $end
$var wire 1 ! D0 $end
$var wire 1 " D1 $end
$var wire 1 F S $end
$var wire 1 C Y $end
$upscope $end
$scope module m3 $end
$var wire 1 D D0 $end
$var wire 1 C D1 $end
$var wire 1 G S $end
$var wire 1 : Y $end
$upscope $end
$upscope $end
$scope module m3 $end
$var wire 1 ; D0 $end
$var wire 1 : D1 $end
$var wire 1 H S $end
$var wire 1 & Y $end
$upscope $end
$upscope $end
$upscope $end
$scope module G4 $end
$var wire 1 ) A $end
$var wire 1 * B $end
$var wire 1 + C $end
$var wire 1 I Y1 $end
$var wire 1 J Y2 $end
$var wire 1 % Y $end
$scope module m1 $end
$var wire 1 I D0 $end
$var wire 1 J D1 $end
$var wire 1 ) S $end
$var wire 1 % Y $end
$upscope $end
$upscope $end
$scope module G5 $end
$var wire 1 ) A $end
$var wire 1 * B $end
$var wire 1 + C $end
$var wire 1 ! G $end
$var wire 1 " V $end
$var wire 1 $ Y $end
$var wire 2 K S1 [1:0] $end
$scope module m1 $end
$var wire 1 L D0 $end
$var wire 1 ! D1 $end
$var wire 1 " D2 $end
$var wire 1 M D3 $end
$var wire 2 N S1 [1:0] $end
$var wire 1 O Y2 $end
$var wire 1 P Y1 $end
$var wire 1 $ Y $end
$scope module m1 $end
$var wire 1 L D0 $end
$var wire 1 ! D1 $end
$var wire 1 Q S $end
$var wire 1 P Y $end
$upscope $end
$scope module m2 $end
$var wire 1 " D0 $end
$var wire 1 M D1 $end
$var wire 1 R S $end
$var wire 1 O Y $end
$upscope $end
$scope module m3 $end
$var wire 1 P D0 $end
$var wire 1 O D1 $end
$var wire 1 S S $end
$var wire 1 $ Y $end
$upscope $end
$upscope $end
$upscope $end
$scope module G6 $end
$var wire 1 ) A $end
$var wire 1 * B $end
$var wire 1 + C $end
$var wire 1 ! G $end
$var wire 1 " V $end
$var wire 1 # Y $end
$var wire 3 T S1 [2:0] $end
$scope module m1 $end
$var wire 1 " D0 $end
$var wire 1 ! D1 $end
$var wire 1 ! D2 $end
$var wire 1 ! D3 $end
$var wire 1 " D4 $end
$var wire 1 " D5 $end
$var wire 1 " D6 $end
$var wire 1 ! D7 $end
$var wire 3 U S1 [2:0] $end
$var wire 1 V Y2 $end
$var wire 1 W Y1 $end
$var wire 1 # Y $end
$scope module m1 $end
$var wire 1 " D0 $end
$var wire 1 ! D1 $end
$var wire 1 ! D2 $end
$var wire 1 ! D3 $end
$var wire 2 X S1 [1:0] $end
$var wire 1 Y Y2 $end
$var wire 1 Z Y1 $end
$var wire 1 W Y $end
$scope module m1 $end
$var wire 1 " D0 $end
$var wire 1 ! D1 $end
$var wire 1 [ S $end
$var wire 1 Z Y $end
$upscope $end
$scope module m2 $end
$var wire 1 ! D0 $end
$var wire 1 ! D1 $end
$var wire 1 \ S $end
$var wire 1 Y Y $end
$upscope $end
$scope module m3 $end
$var wire 1 Z D0 $end
$var wire 1 Y D1 $end
$var wire 1 ] S $end
$var wire 1 W Y $end
$upscope $end
$upscope $end
$scope module m2 $end
$var wire 1 " D0 $end
$var wire 1 " D1 $end
$var wire 1 " D2 $end
$var wire 1 ! D3 $end
$var wire 2 ^ S1 [1:0] $end
$var wire 1 _ Y2 $end
$var wire 1 ` Y1 $end
$var wire 1 V Y $end
$scope module m1 $end
$var wire 1 " D0 $end
$var wire 1 " D1 $end
$var wire 1 a S $end
$var wire 1 ` Y $end
$upscope $end
$scope module m2 $end
$var wire 1 " D0 $end
$var wire 1 ! D1 $end
$var wire 1 b S $end
$var wire 1 _ Y $end
$upscope $end
$scope module m3 $end
$var wire 1 ` D0 $end
$var wire 1 _ D1 $end
$var wire 1 c S $end
$var wire 1 V Y $end
$upscope $end
$upscope $end
$scope module m3 $end
$var wire 1 W D0 $end
$var wire 1 V D1 $end
$var wire 1 d S $end
$var wire 1 # Y $end
$upscope $end
$upscope $end
$upscope $end
$upscope $end
$enddefinitions $end
#0
$dumpvars
0d
0c
0b
0a
1`
1_
b0 ^
0]
0\
0[
1Z
0Y
b0 X
1W
1V
b0 U
b0 T
0S
0R
0Q
1P
1O
b0 N
1M
1L
b0 K
1J
1I
0H
0G
0F
0E
1D
0C
b0 B
0A
0@
0?
0>
1=
b0 <
0;
1:
b0 9
b0 8
07
06
05
04
13
b0 2
11
10
b0 /
1.
1-
0,
0+
0*
0)
0(
0'
0&
1%
1$
1#
1"
0!
$end
#1
1&
0#
1;
0:
0W
1>
0=
0D
1C
0$
0Z
0_
1(
0-
03
1'
1?
1@
1E
1F
0%
0P
1[
1\
1a
1b
1,
0.
00
01
14
b1 <
b1 B
0I
0L
0M
b1 X
b1 ^
b1 8
b1 9
b1 T
b1 U
1+
#2
1&
0>
1=
1;
1D
0C
0:
1Z
1_
1V
1'
0?
0@
1A
0E
0F
1G
0[
0\
1]
0a
0b
1c
1.
10
11
14
1L
1M
15
16
b10 <
b10 B
1Q
1R
b10 X
b10 ^
0+
b1 /
b1 2
b10 8
b10 9
b1 K
b1 N
b10 T
b10 U
1*
#3
0&
0;
1:
0V
0'
1>
0=
0D
1C
0Z
0_
0(
1-
04
1?
1@
1E
1F
0J
0O
1[
1\
1a
1b
0,
0.
00
01
13
b11 <
b11 B
0L
0M
b11 X
b11 ^
b11 8
b11 9
b11 T
b11 U
1+
#4
1W
1#
1'
0>
1=
0;
1D
0C
1:
1%
1$
1Z
1_
1V
0?
0@
0A
0E
0F
0G
1J
1P
1O
0[
0\
0]
0a
0b
0c
1&
1.
10
11
13
1L
1M
05
06
b0 <
b0 B
1I
0Q
0R
b0 X
b0 ^
1(
17
1H
1S
1d
0+
0*
b10 /
b10 2
b100 8
b100 9
b10 K
b10 N
b100 T
b100 U
1)
#5
0&
1;
0:
0W
0(
0'
1>
0=
0D
1C
0Z
0_
0-
03
1?
1@
1E
1F
0P
1[
1\
1a
1b
1,
0.
00
01
14
b1 <
b1 B
0I
0L
0M
b1 X
b1 ^
b101 8
b101 9
b101 T
b101 U
1+
#6
0&
1#
0>
1=
1;
1D
0C
0:
1Z
1_
1V
0?
0@
1A
0E
0F
1G
0[
0\
1]
0a
0b
1c
1.
10
11
14
1L
1M
15
16
b10 <
b10 B
1Q
1R
b10 X
b10 ^
0+
b11 /
b11 2
b110 8
b110 9
b11 K
b11 N
b110 T
b110 U
1*
#7
1&
0#
0;
1:
0V
1(
1>
0=
0D
1C
0%
0$
0Z
0_
1-
04
1'
1?
1@
1E
1F
0J
0O
1[
1\
1a
1b
0,
0.
00
01
13
b11 <
b11 B
0L
0M
b11 X
b11 ^
b111 8
b111 9
b111 T
b111 U
1+
#8
1#
1W
0>
1=
0;
1D
0C
1:
1$
1Z
1_
1V
0?
0@
0A
0E
0F
0G
1%
1J
1P
1O
0[
0\
0]
0a
0b
0c
0'
0&
1.
10
11
13
1L
1M
05
06
b0 <
b0 B
1I
0Q
0R
b0 X
b0 ^
0(
07
0H
0S
0d
0+
0*
b0 /
b0 2
b0 8
b0 9
b0 K
b0 N
b0 T
b0 U
0)
#9
1&
0#
1;
0:
0W
1>
0=
0D
1C
0$
0Z
0_
1(
0-
03
1'
1?
1@
1E
1F
0%
0P
1[
1\
1a
1b
1,
0.
00
01
14
b1 <
b1 B
0I
0L
0M
b1 X
b1 ^
b1 8
b1 9
b1 T
b1 U
1+
#10
1&
0>
1=
1;
1D
0C
0:
1Z
1_
1V
1'
0?
0@
1A
0E
0F
1G
0[
0\
1]
0a
0b
1c
1.
10
11
14
1L
1M
15
16
b10 <
b10 B
1Q
1R
b10 X
b10 ^
0+
b1 /
b1 2
b10 8
b10 9
b1 K
b1 N
b10 T
b10 U
1*
#11
0&
0;
1:
0V
0'
1>
0=
0D
1C
0Z
0_
0(
1-
04
1?
1@
1E
1F
0J
0O
1[
1\
1a
1b
0,
0.
00
01
13
b11 <
b11 B
0L
0M
b11 X
b11 ^
b11 8
b11 9
b11 T
b11 U
1+
#12
1W
1#
1'
0>
1=
0;
1D
0C
1:
1%
1$
1Z
1_
1V
0?
0@
0A
0E
0F
0G
1J
1P
1O
0[
0\
0]
0a
0b
0c
1&
1.
10
11
13
1L
1M
05
06
b0 <
b0 B
1I
0Q
0R
b0 X
b0 ^
1(
17
1H
1S
1d
0+
0*
b10 /
b10 2
b100 8
b100 9
b10 K
b10 N
b100 T
b100 U
1)
#13
0&
1;
0:
0W
0(
0'
1>
0=
0D
1C
0Z
0_
0-
03
1?
1@
1E
1F
0P
1[
1\
1a
1b
1,
0.
00
01
14
b1 <
b1 B
0I
0L
0M
b1 X
b1 ^
b101 8
b101 9
b101 T
b101 U
1+
#14
0&
1#
0>
1=
1;
1D
0C
0:
1Z
1_
1V
0?
0@
1A
0E
0F
1G
0[
0\
1]
0a
0b
1c
1.
10
11
14
1L
1M
15
16
b10 <
b10 B
1Q
1R
b10 X
b10 ^
0+
b11 /
b11 2
b110 8
b110 9
b11 K
b11 N
b110 T
b110 U
1*
#15
1&
0#
0;
1:
0V
1(
1>
0=
0D
1C
0%
0$
0Z
0_
1-
04
1'
1?
1@
1E
1F
0J
0O
1[
1\
1a
1b
0,
0.
00
01
13
b11 <
b11 B
0L
0M
b11 X
b11 ^
b111 8
b111 9
b111 T
b111 U
1+
#16
1#
1W
0>
1=
0;
1D
0C
1:
1$
1Z
1_
1V
0?
0@
0A
0E
0F
0G
1%
1J
1P
1O
0[
0\
0]
0a
0b
0c
0'
0&
1.
10
11
13
1L
1M
05
06
b0 <
b0 B
1I
0Q
0R
b0 X
b0 ^
0(
07
0H
0S
0d
0+
0*
b0 /
b0 2
b0 8
b0 9
b0 K
b0 N
b0 T
b0 U
0)
#17
1&
0#
1;
0:
0W
1>
0=
0D
1C
0$
0Z
0_
1(
0-
03
1'
1?
1@
1E
1F
0%
0P
1[
1\
1a
1b
1,
0.
00
01
14
b1 <
b1 B
0I
0L
0M
b1 X
b1 ^
b1 8
b1 9
b1 T
b1 U
1+
#18
1&
0>
1=
1;
1D
0C
0:
1Z
1_
1V
1'
0?
0@
1A
0E
0F
1G
0[
0\
1]
0a
0b
1c
1.
10
11
14
1L
1M
15
16
b10 <
b10 B
1Q
1R
b10 X
b10 ^
0+
b1 /
b1 2
b10 8
b10 9
b1 K
b1 N
b10 T
b10 U
1*
#19
0&
0;
1:
0V
0'
1>
0=
0D
1C
0Z
0_
0(
1-
04
1?
1@
1E
1F
0J
0O
1[
1\
1a
1b
0,
0.
00
01
13
b11 <
b11 B
0L
0M
b11 X
b11 ^
b11 8
b11 9
b11 T
b11 U
1+
#20
1W
1#
1'
0>
1=
0;
1D
0C
1:
1%
1$
1Z
1_
1V
0?
0@
0A
0E
0F
0G
1J
1P
1O
0[
0\
0]
0a
0b
0c
1&
1.
10
11
13
1L
1M
05
06
b0 <
b0 B
1I
0Q
0R
b0 X
b0 ^
1(
17
1H
1S
1d
0+
0*
b10 /
b10 2
b100 8
b100 9
b10 K
b10 N
b100 T
b100 U
1)
#21
0&
1;
0:
0W
0(
0'
1>
0=
0D
1C
0Z
0_
0-
03
1?
1@
1E
1F
0P
1[
1\
1a
1b
1,
0.
00
01
14
b1 <
b1 B
0I
0L
0M
b1 X
b1 ^
b101 8
b101 9
b101 T
b101 U
1+
#22
0&
1#
0>
1=
1;
1D
0C
0:
1Z
1_
1V
0?
0@
1A
0E
0F
1G
0[
0\
1]
0a
0b
1c
1.
10
11
14
1L
1M
15
16
b10 <
b10 B
1Q
1R
b10 X
b10 ^
0+
b11 /
b11 2
b110 8
b110 9
b11 K
b11 N
b110 T
b110 U
1*
#23
1&
0#
0;
1:
0V
1(
1>
0=
0D
1C
0%
0$
0Z
0_
1-
04
1'
1?
1@
1E
1F
0J
0O
1[
1\
1a
1b
0,
0.
00
01
13
b11 <
b11 B
0L
0M
b11 X
b11 ^
b111 8
b111 9
b111 T
b111 U
1+
#24
1#
1W
0>
1=
0;
1D
0C
1:
1$
1Z
1_
1V
0?
0@
0A
0E
0F
0G
1%
1J
1P
1O
0[
0\
0]
0a
0b
0c
0'
0&
1.
10
11
13
1L
1M
05
06
b0 <
b0 B
1I
0Q
0R
b0 X
b0 ^
0(
07
0H
0S
0d
0+
0*
b0 /
b0 2
b0 8
b0 9
b0 K
b0 N
b0 T
b0 U
0)
#25
1&
0#
1;
0:
0W
1>
0=
0D
1C
0$
0Z
0_
1(
0-
03
1'
1?
1@
1E
1F
0%
0P
1[
1\
1a
1b
1,
0.
00
01
14
b1 <
b1 B
0I
0L
0M
b1 X
b1 ^
b1 8
b1 9
b1 T
b1 U
1+
#26
1&
0>
1=
1;
1D
0C
0:
1Z
1_
1V
1'
0?
0@
1A
0E
0F
1G
0[
0\
1]
0a
0b
1c
1.
10
11
14
1L
1M
15
16
b10 <
b10 B
1Q
1R
b10 X
b10 ^
0+
b1 /
b1 2
b10 8
b10 9
b1 K
b1 N
b10 T
b10 U
1*
#27
0&
0;
1:
0V
0'
1>
0=
0D
1C
0Z
0_
0(
1-
04
1?
1@
1E
1F
0J
0O
1[
1\
1a
1b
0,
0.
00
01
13
b11 <
b11 B
0L
0M
b11 X
b11 ^
b11 8
b11 9
b11 T
b11 U
1+
#28
1W
1#
1'
0>
1=
0;
1D
0C
1:
1%
1$
1Z
1_
1V
0?
0@
0A
0E
0F
0G
1J
1P
1O
0[
0\
0]
0a
0b
0c
1&
1.
10
11
13
1L
1M
05
06
b0 <
b0 B
1I
0Q
0R
b0 X
b0 ^
1(
17
1H
1S
1d
0+
0*
b10 /
b10 2
b100 8
b100 9
b10 K
b10 N
b100 T
b100 U
1)
#29
0&
1;
0:
0W
0(
0'
1>
0=
0D
1C
0Z
0_
0-
03
1?
1@
1E
1F
0P
1[
1\
1a
1b
1,
0.
00
01
14
b1 <
b1 B
0I
0L
0M
b1 X
b1 ^
b101 8
b101 9
b101 T
b101 U
1+
#30
0&
1#
0>
1=
1;
1D
0C
0:
1Z
1_
1V
0?
0@
1A
0E
0F
1G
0[
0\
1]
0a
0b
1c
1.
10
11
14
1L
1M
15
16
b10 <
b10 B
1Q
1R
b10 X
b10 ^
0+
b11 /
b11 2
b110 8
b110 9
b11 K
b11 N
b110 T
b110 U
1*
#31
1&
0#
0;
1:
0V
1(
1>
0=
0D
1C
0%
0$
0Z
0_
1-
04
1'
1?
1@
1E
1F
0J
0O
1[
1\
1a
1b
0,
0.
00
01
13
b11 <
b11 B
0L
0M
b11 X
b11 ^
b111 8
b111 9
b111 T
b111 U
1+
#32
1#
1W
0>
1=
0;
1D
0C
1:
1$
1Z
1_
1V
0?
0@
0A
0E
0F
0G
1%
1J
1P
1O
0[
0\
0]
0a
0b
0c
0'
0&
1.
10
11
13
1L
1M
05
06
b0 <
b0 B
1I
0Q
0R
b0 X
b0 ^
0(
07
0H
0S
0d
0+
0*
b0 /
b0 2
b0 8
b0 9
b0 K
b0 N
b0 T
b0 U
0)
#33
1&
0#
1;
0:
0W
1>
0=
0D
1C
0$
0Z
0_
1(
0-
03
1'
1?
1@
1E
1F
0%
0P
1[
1\
1a
1b
1,
0.
00
01
14
b1 <
b1 B
0I
0L
0M
b1 X
b1 ^
b1 8
b1 9
b1 T
b1 U
1+
#34
1&
0>
1=
1;
1D
0C
0:
1Z
1_
1V
1'
0?
0@
1A
0E
0F
1G
0[
0\
1]
0a
0b
1c
1.
10
11
14
1L
1M
15
16
b10 <
b10 B
1Q
1R
b10 X
b10 ^
0+
b1 /
b1 2
b10 8
b10 9
b1 K
b1 N
b10 T
b10 U
1*
#35
0&
0;
1:
0V
0'
1>
0=
0D
1C
0Z
0_
0(
1-
04
1?
1@
1E
1F
0J
0O
1[
1\
1a
1b
0,
0.
00
01
13
b11 <
b11 B
0L
0M
b11 X
b11 ^
b11 8
b11 9
b11 T
b11 U
1+
#36
1W
1#
1'
0>
1=
0;
1D
0C
1:
1%
1$
1Z
1_
1V
0?
0@
0A
0E
0F
0G
1J
1P
1O
0[
0\
0]
0a
0b
0c
1&
1.
10
11
13
1L
1M
05
06
b0 <
b0 B
1I
0Q
0R
b0 X
b0 ^
1(
17
1H
1S
1d
0+
0*
b10 /
b10 2
b100 8
b100 9
b10 K
b10 N
b100 T
b100 U
1)
#37
0&
1;
0:
0W
0(
0'
1>
0=
0D
1C
0Z
0_
0-
03
1?
1@
1E
1F
0P
1[
1\
1a
1b
1,
0.
00
01
14
b1 <
b1 B
0I
0L
0M
b1 X
b1 ^
b101 8
b101 9
b101 T
b101 U
1+
#38
0&
1#
0>
1=
1;
1D
0C
0:
1Z
1_
1V
0?
0@
1A
0E
0F
1G
0[
0\
1]
0a
0b
1c
1.
10
11
14
1L
1M
15
16
b10 <
b10 B
1Q
1R
b10 X
b10 ^
0+
b11 /
b11 2
b110 8
b110 9
b11 K
b11 N
b110 T
b110 U
1*
#39
1&
0#
0;
1:
0V
1(
1>
0=
0D
1C
0%
0$
0Z
0_
1-
04
1'
1?
1@
1E
1F
0J
0O
1[
1\
1a
1b
0,
0.
00
01
13
b11 <
b11 B
0L
0M
b11 X
b11 ^
b111 8
b111 9
b111 T
b111 U
1+
#40
1#
1W
0>
1=
0;
1D
0C
1:
1$
1Z
1_
1V
0?
0@
0A
0E
0F
0G
1%
1J
1P
1O
0[
0\
0]
0a
0b
0c
0'
0&
1.
10
11
13
1L
1M
05
06
b0 <
b0 B
1I
0Q
0R
b0 X
b0 ^
0(
07
0H
0S
0d
0+
0*
b0 /
b0 2
b0 8
b0 9
b0 K
b0 N
b0 T
b0 U
0)
#41
1&
0#
1;
0:
0W
1>
0=
0D
1C
0$
0Z
0_
1(
0-
03
1'
1?
1@
1E
1F
0%
0P
1[
1\
1a
1b
1,
0.
00
01
14
b1 <
b1 B
0I
0L
0M
b1 X
b1 ^
b1 8
b1 9
b1 T
b1 U
1+
#42
1&
0>
1=
1;
1D
0C
0:
1Z
1_
1V
1'
0?
0@
1A
0E
0F
1G
0[
0\
1]
0a
0b
1c
1.
10
11
14
1L
1M
15
16
b10 <
b10 B
1Q
1R
b10 X
b10 ^
0+
b1 /
b1 2
b10 8
b10 9
b1 K
b1 N
b10 T
b10 U
1*
#43
0&
0;
1:
0V
0'
1>
0=
0D
1C
0Z
0_
0(
1-
04
1?
1@
1E
1F
0J
0O
1[
1\
1a
1b
0,
0.
00
01
13
b11 <
b11 B
0L
0M
b11 X
b11 ^
b11 8
b11 9
b11 T
b11 U
1+
#44
1W
1#
1'
0>
1=
0;
1D
0C
1:
1%
1$
1Z
1_
1V
0?
0@
0A
0E
0F
0G
1J
1P
1O
0[
0\
0]
0a
0b
0c
1&
1.
10
11
13
1L
1M
05
06
b0 <
b0 B
1I
0Q
0R
b0 X
b0 ^
1(
17
1H
1S
1d
0+
0*
b10 /
b10 2
b100 8
b100 9
b10 K
b10 N
b100 T
b100 U
1)
#45
0&
1;
0:
0W
0(
0'
1>
0=
0D
1C
0Z
0_
0-
03
1?
1@
1E
1F
0P
1[
1\
1a
1b
1,
0.
00
01
14
b1 <
b1 B
0I
0L
0M
b1 X
b1 ^
b101 8
b101 9
b101 T
b101 U
1+
#46
0&
1#
0>
1=
1;
1D
0C
0:
1Z
1_
1V
0?
0@
1A
0E
0F
1G
0[
0\
1]
0a
0b
1c
1.
10
11
14
1L
1M
15
16
b10 <
b10 B
1Q
1R
b10 X
b10 ^
0+
b11 /
b11 2
b110 8
b110 9
b11 K
b11 N
b110 T
b110 U
1*
