Laboratorio_9/Ejercicio_01/Ejercicio_01.v
// Electrónica digital
// Valerie Valdez 19659

//                             Laboratorio #09
//                              Ejercicio 01



// Flip Flop D 1 bit

module FFD(input wire clk, EN, reset, input wire C, output reg D);
  always @ (posedge clk, posedge reset) begin

// Non-blockinf assigment
    if(reset) // Colocar todos los valores en 0
      D <= 1'b0;

    else if(EN == 1) // Enabled encendido cuenta cuenta cada flanco del reloj
      D <= C;
  end
endmodule




// Flip Flop 2 bits

module FFD2(input wire clk, EN, reset, input wire [1:0]C, output [1:0]D);

  FFD A1(clk, EN, reset, C[0], D[0]);
  FFD A2(clk, EN, reset, C[1], D[1]);

endmodule



// Flip Flop 4 bits

module FFD4(input wire clk, EN, reset, input wire [3:0]C, output [3:0]D);

    FFD2 B1(clk, EN, reset, C[3:2], D[3:2]);
    FFD2 B2(clk, EN, reset, C[1:0], D[1:0]);

endmodule

Laboratorio_9/Ejercicio_01/Ejercicio_01_tb.v
// Electrónica digital
// Valerie Valdez 19659

//                             Laboratorio #09
//                              Ejercicio 01

//Testbench para los Flip Flop

module testbench();

  //inputs
  reg clk, EN, reset, reset1, reset2;
  reg C;
  reg [1:0]C1;
  reg [3:0]C2;

  //outputs
  wire D;
  wire [1:0]D1;
  wire [3:0]D2;


// Clock
  always
    #1 clk = ~clk;


// Llamar a los módulos
  FFD A1(clk, EN, reset, C, D); // Flitidiflop 1 bit
  FFD2 B1(clk, EN, reset1, C1, D1); // Flitidiflop 2 bits
  FFD4 R1(clk, EN, reset2, C2, D2); // Flitidiflop 4 bits


  initial begin
    #1
    $display("\n");
    $display("Flip Flop de 1 bit");
    $display("\n");
    $display("-------------------|-----|");
    $display(" clk  EN  reset  C  |  D  |");
    $display("-------------------|-----|");
    $monitor("%b    %b    %b    %b   |  %b  |", clk, EN, reset, C, D);

    #1 clk = 0; reset = 0; EN = 1; C = 0;
    #5 reset = 1; EN = 1; C = 0;
    #5 reset = 0; EN = 1; C = 0;
    #5 C = 1;
    #5 C = 0;
    #5 EN = 0;
    #5 C = 1;

  end


// Prueba del FFD de dos bits
  initial begin
    #34
    $display("\n");
    $display("Flip Flop de 2 bit");
    $display("\n");
    $display("-------------------|-----|");
    $display(" clk  EN  reset  C  |  D  |");
    $display("-------------------|-----|");
    $monitor("%b    %b    %b    %b  | %b  |", clk, EN, reset1, C1, D1);

    #1 clk = 0; reset1 = 0; EN = 0; C1 = 2'b00;
    #5 reset1 = 1; EN = 1; C1 = 2'b00;
    #5 reset1 = 0; EN = 1; C1 = 2'b00;
    #5 C1 = 2'b11;
    #5 C1 = 2'b00;
    #5 EN = 0;
    #5 C1 = 2'b11;

  end


// Prueba del FFD de 4 bits
initial begin
  #70
  $display("\n");
  $display("Flip Flop de 4 bit");
  $display("\n");
  $display("---------------------|-------|");
  $display(" clk  EN  reset   C   |   D   |");
  $display("---------------------|-------|");
  $monitor("%b    %b    %b    %b  | %b  | ", clk, EN, reset2, C2, D2);

  #1 clk = 0; reset2 = 1; EN = 1; C2 = 4'b0000;
  #5 reset2 = 0; EN = 1; C2 = 4'b0000;
  #5 reset2 = 0; EN = 1; C2 = 4'b0000;
  #5 C2 = 4'b1111;
  #5 C2 = 4'b0000;
  #5 EN = 0;
  #5 C2 = 4'b1111;

end


  initial
    #110 $finish;

// GTKwave para el diagrama de timing
  initial begin
    $dumpfile("Ejercicio_01_tb.vcd");
    $dumpvars(0, testbench);
  end
endmodule

Laboratorio_9/Ejercicio_01/Ejercicio_01_tb.vcd
$date
	Fri Oct 30 23:18:25 2020
$end
$version
	Icarus Verilog
$end
$timescale
	1ps
$end
$scope module testbench $end
$var wire 4 ! D2 [3:0] $end
$var wire 2 " D1 [1:0] $end
$var wire 1 # D $end
$var reg 1 $ C $end
$var reg 2 % C1 [1:0] $end
$var reg 4 & C2 [3:0] $end
$var reg 1 ' EN $end
$var reg 1 ( clk $end
$var reg 1 ) reset $end
$var reg 1 * reset1 $end
$var reg 1 + reset2 $end
$scope module A1 $end
$var wire 1 $ C $end
$var wire 1 ' EN $end
$var wire 1 ( clk $end
$var wire 1 ) reset $end
$var reg 1 # D $end
$upscope $end
$scope module B1 $end
$var wire 2 , C [1:0] $end
$var wire 1 ' EN $end
$var wire 1 ( clk $end
$var wire 1 * reset $end
$var wire 2 - D [1:0] $end
$scope module A1 $end
$var wire 1 . C $end
$var wire 1 ' EN $end
$var wire 1 ( clk $end
$var wire 1 * reset $end
$var reg 1 / D $end
$upscope $end
$scope module A2 $end
$var wire 1 0 C $end
$var wire 1 ' EN $end
$var wire 1 ( clk $end
$var wire 1 * reset $end
$var reg 1 1 D $end
$upscope $end
$upscope $end
$scope module R1 $end
$var wire 4 2 C [3:0] $end
$var wire 1 ' EN $end
$var wire 1 ( clk $end
$var wire 1 + reset $end
$var wire 4 3 D [3:0] $end
$scope module B1 $end
$var wire 2 4 C [1:0] $end
$var wire 1 ' EN $end
$var wire 1 ( clk $end
$var wire 1 + reset $end
$var wire 2 5 D [1:0] $end
$scope module A1 $end
$var wire 1 6 C $end
$var wire 1 ' EN $end
$var wire 1 ( clk $end
$var wire 1 + reset $end
$var reg 1 7 D $end
$upscope $end
$scope module A2 $end
$var wire 1 8 C $end
$var wire 1 ' EN $end
$var wire 1 ( clk $end
$var wire 1 + reset $end
$var reg 1 9 D $end
$upscope $end
$upscope $end
$scope module B2 $end
$var wire 2 : C [1:0] $end
$var wire 1 ' EN $end
$var wire 1 ( clk $end
$var wire 1 + reset $end
$var wire 2 ; D [1:0] $end
$scope module A1 $end
$var wire 1 < C $end
$var wire 1 ' EN $end
$var wire 1 ( clk $end
$var wire 1 + reset $end
$var reg 1 = D $end
$upscope $end
$scope module A2 $end
$var wire 1 > C $end
$var wire 1 ' EN $end
$var wire 1 ( clk $end
$var wire 1 + reset $end
$var reg 1 ? D $end
$upscope $end
$upscope $end
$upscope $end
$upscope $end
$enddefinitions $end
#0
$dumpvars
x?
x>
x=
x<
bx ;
bx :
x9
x8
x7
x6
bx 5
bx 4
bx 3
bx 2
x1
x0
x/
x.
bx -
bx ,
x+
x*
x)
x(
x'
bx &
bx %
x$
x#
bx "
bx !
$end
#2
0$
1'
0)
0(
#3
0#
1(
#4
0(
#5
1(
#6
0(
#7
1(
1)
#8
0(
#9
1(
#10
0(
#11
1(
#12
0(
0)
#13
1(
#14
0(
#15
1(
#16
0(
#17
1#
1(
1$
#18
0(
#19
1(
#20
0(
#21
1(
#22
0(
0$
#23
0#
1(
#24
0(
#25
1(
#26
0(
#27
1(
0'
#28
0(
#29
1(
#30
0(
#31
1(
#32
0(
1$
#33
1(
#34
0(
#35
0.
00
1(
b0 %
b0 ,
0*
#36
0(
#37
1(
#38
0(
#39
1(
#40
01
b0 "
b0 -
0/
0(
1'
1*
#41
1#
1(
#42
0(
#43
1(
#44
0(
#45
1(
0*
#46
0(
#47
1(
#48
0(
#49
1(
#50
1.
10
0(
b11 %
b11 ,
#51
11
b11 "
b11 -
1/
1(
#52
0(
#53
1(
#54
0(
#55
01
b0 "
b0 -
0/
0.
00
1(
b0 %
b0 ,
#56
0(
#57
1(
#58
0(
#59
1(
#60
0(
0'
#61
1(
#62
0(
#63
1(
#64
0(
#65
1.
10
1(
b11 %
b11 ,
#66
0(
#67
1(
#68
0(
#69
1(
#70
0(
#71
11
b11 "
b11 -
1/
07
b0 5
09
0=
b0 !
b0 3
b0 ;
0?
06
08
0<
0>
b0 4
b0 :
1(
b0 &
b0 2
1'
1+
#72
0(
#73
1(
#74
0(
#75
1(
#76
0(
0+
#77
1(
#78
0(
#79
1(
#80
0(
#81
1(
#82
0(
#83
1(
#84
0(
#85
1(
#86
16
18
1<
1>
b11 4
b11 :
0(
b1111 &
b1111 2
#87
17
b11 5
19
1=
b1111 !
b1111 3
b11 ;
1?
1(
#88
0(
#89
1(
#90
0(
#91
06
08
0<
0>
b0 4
b0 :
1(
b0 &
b0 2
#92
0(
#93
0?
b0 ;
0=
09
b0 !
b0 3
b0 5
07
1(
#94
0(
#95
1(
#96
0(
0'
#97
1(
#98
0(
#99
1(
#100
0(
#101
16
18
1<
1>
b11 4
b11 :
1(
b1111 &
b1111 2
