Laboratorio_10/Ejercicio_1/Lab10.v
// Universidad del Valle de Guatemala
// Valerie Valdez


//                      Electrónica digital
//                         Laboratorio 10
//                         Ejercicio No. 2


// Flip Flop 4 bits tipo D de 4 bits con reset síncrono y asíncrono
module FFD4(input wire clk, reset, EN,
  input wire [3:0]C,
  output reg [3:0]D);

// Con always una sección del código estará siempre activado
  always @ (posedge clk, posedge reset) begin // Count on the rising edge of the clk

      if(reset) begin // En caso de reset colocar todas las salidas en 0
        D <= 4'b0;
      end

      else if (EN) begin // Entrada igual a la salida
        D <= C;
      end
  end
endmodule


// Flip Flop tipo D de 8 bits
module FETCH(input wire clk, reset, EN, input wire [7:0]D, output wire[3:0]instr, oprnd);

  FFD4 A1(clk, reset, EN, D[7:4], instr); // bits más significativos
  FFD4 B1(clk, reset, EN, D[3:0], oprnd); // bits menos significativos
endmodule



// Implementar un contador de 12 bits con un enable y capaz de hacer un load
module contador(input wire clk, rst, EN, blo,
  input wire [11:0]load,
  output reg [11:0]val);


// Non-blocking assigment
    always @(posedge clk or posedge rst or posedge blo) begin

      if(rst == 1) // Colocar todos los valores en 0
        val <= 12'b0;

      else if(EN == 1) //Enabled encendido cuenta en cada flanco de reloj
        val <= val + 1;

      else if(blo == 1) // Blo encendido entonces Load comienza a contar
        val <= load;

        end
endmodule


// Implementación de la memoria ROM de 4Kx8
module Mrom(input wire [11:0]address,
  output wire [7:0]D); // Tamaño del dato de 8 bits

  reg[7:0] Mrom[0:4095]; // Ancho y localidades de memoria


// Inicializar la memoria
  initial begin
    $readmemb("Mrom.list", Mrom); // Leer los valores de la lista en binario
  end

  assign D = Mrom[address]; // Asignarle el valor en la dirección dada
endmodule



// Integrando todo
module integrador(input wire clk, reset, ENPC, ENF, blo, input wire [11:0]load, output wire [7:0]P_B, output wire [3:0]instr, output wire [3:0]oprnd);
  wire [11:0]PC;
  contador C1(clk, reset, ENPC, blo, load, PC);
  Mrom C2(PC, P_B);
  FETCH C3(clk, reset, ENF, P_B, instr, oprnd);

endmodule

Laboratorio_10/Ejercicio_1/Lab10_tb.v
/// Universidad del Valle de Guatemala
// Valerie Valde (19659)

//                      Electrónica digital
//                         Laboratorio 10
//                         Ejercicio No. 1


// Testbench del circuito mostrado en el diagrama

module testbench();
  reg clk, reset, ENPC, ENF, blo;
  reg [11:0]load;
  wire [7:0]P_B;
  wire[3:0]instr;
  wire [3:0]oprnd;


  // Reloj de una unidad de tiempo con cambio en el flanco
  always
      #1 clk = ~clk;

  // Iteración del módulo
  integrador U(clk, reset, ENPC, ENF, blo, load, P_B, instr, oprnd);


  // Prueba para el Flip Flop tipo D de 8 bits
  initial begin
    #1
    $display("\n");
    $display(" Programa ");
    $display("\n");
    $display("-----------------------------|--------------------------|");
    $display("Clk reset ENPC ENF blo load  |   P_B     instr    oprnd |");
    $display("-----------------------------|--------------------------|");
    $monitor("%b  %b  %b  %b  %b  %b  | %b   %b    %b  |", clk, reset, ENPC, ENF, blo, load, P_B, instr, oprnd);

    clk = 0; reset = 1; ENF = 0; ENPC = 0; blo = 0; load = 12'b000000000000;
    #2 reset = 0; ENF = 1; ENPC = 1; blo = 0;
    #2 reset = 0; ENF = 1; ENPC = 1; blo = 0;
    #2 reset = 0; load = 12'b000000000100;
    #2 reset = 0; ENF = 1; ENPC = 1; blo = 1;
    #3 reset = 0; ENF = 0; ENPC = 0; blo = 0;

  end


  initial
    #35 $finish;

// GTK wave
  initial begin
    $dumpfile("Lab10_tb.vcd");
    $dumpvars(0, testbench);
  end
endmodule

Laboratorio_10/Ejercicio_1/Lab10_tb.vcd
$date
	Sat Nov 07 00:32:55 2020
$end
$version
	Icarus Verilog
$end
$timescale
	1ps
$end
$scope module testbench $end
$var wire 4 ! oprnd [3:0] $end
$var wire 4 " instr [3:0] $end
$var wire 8 # P_B [7:0] $end
$var reg 1 $ ENF $end
$var reg 1 % ENPC $end
$var reg 1 & blo $end
$var reg 1 ' clk $end
$var reg 12 ( load [11:0] $end
$var reg 1 ) reset $end
$scope module U $end
$var wire 1 $ ENF $end
$var wire 1 % ENPC $end
$var wire 1 & blo $end
$var wire 1 ' clk $end
$var wire 12 * load [11:0] $end
$var wire 1 ) reset $end
$var wire 4 + oprnd [3:0] $end
$var wire 4 , instr [3:0] $end
$var wire 8 - P_B [7:0] $end
$var wire 12 . PC [11:0] $end
$scope module C1 $end
$var wire 1 % EN $end
$var wire 1 & blo $end
$var wire 1 ' clk $end
$var wire 12 / load [11:0] $end
$var wire 1 ) rst $end
$var reg 12 0 val [11:0] $end
$upscope $end
$scope module C2 $end
$var wire 8 1 D [7:0] $end
$var wire 12 2 address [11:0] $end
$upscope $end
$scope module C3 $end
$var wire 8 3 D [7:0] $end
$var wire 1 $ EN $end
$var wire 1 ' clk $end
$var wire 1 ) reset $end
$var wire 4 4 oprnd [3:0] $end
$var wire 4 5 instr [3:0] $end
$scope module A1 $end
$var wire 4 6 C [3:0] $end
$var wire 1 $ EN $end
$var wire 1 ' clk $end
$var wire 1 ) reset $end
$var reg 4 7 D [3:0] $end
$upscope $end
$scope module B1 $end
$var wire 4 8 C [3:0] $end
$var wire 1 $ EN $end
$var wire 1 ' clk $end
$var wire 1 ) reset $end
$var reg 4 9 D [3:0] $end
$upscope $end
$upscope $end
$upscope $end
$upscope $end
$enddefinitions $end
#0
$dumpvars
bx 9
bx 8
bx 7
bx 6
bx 5
bx 4
bx 3
bx 2
bx 1
bx 0
bx /
bx .
bx -
bx ,
bx +
bx *
x)
bx (
x'
x&
x%
x$
bx #
bx "
bx !
$end
#1
b0 6
b0 8
b0 #
b0 -
b0 1
b0 3
b0 .
b0 0
b0 2
b0 "
b0 ,
b0 5
b0 7
b0 !
b0 +
b0 4
b0 9
b0 (
b0 *
b0 /
0&
0%
0$
1)
0'
#2
1'
#3
0'
1%
1$
0)
#4
b1111 6
b11110000 #
b11110000 -
b11110000 1
b11110000 3
b1 .
b1 0
b1 2
1'
#5
0'
#6
b11 6
b1010 8
b111010 #
b111010 -
b111010 1
b111010 3
b10 .
b10 0
b10 2
b1111 "
b1111 ,
b1111 5
b1111 7
1'
#7
0'
b100 (
b100 *
b100 /
#8
b1110 6
b1100 8
b11101100 #
b11101100 -
b11101100 1
b11101100 3
b11 .
b11 0
b11 2
b11 "
b11 ,
b11 5
b11 7
b1010 !
b1010 +
b1010 4
b1010 9
1'
#9
b110 6
b0 8
b1100000 #
b1100000 -
b1100000 1
b1100000 3
b100 .
b100 0
b100 2
0'
1&
#10
b111 6
b1000 8
b1111000 #
b1111000 -
b1111000 1
b1111000 3
b101 .
b101 0
b101 2
b0 !
b0 +
b0 4
b0 9
b110 "
b110 ,
b110 5
b110 7
1'
#11
0'
#12
1'
0&
0%
0$
