Laboratorio_8/Memoria_rom/Memoria_rom.v
// Universidad del Valle de Guatemala
// Valerie Valdez

//                         Electrónica digital
//                            Laboratorio 8


// Implementación de la memoria ROM de 4Kx8
module Mrom(input wire [11:0]address,
  output wire [7:0]D); // Tamaño del dato de 8 bits

  reg[7:0] Mrom[0:4095]; // Ancho y localidades de memoria

// Inicializar la memoria
  initial begin
    $readmemb("Mrom.list", Mrom); // Leer los valores de la lista en binario
  end

  assign D = Mrom[address]; // Asignarle el valor en la dirección dada
endmodule

Laboratorio_8/Memoria_rom/Memoria_rom_tb.v
// Universidad del Valle de Guatemala
// Valerie Valdez

//                         Electrónica digital
//                            Laboratorio 8


// Módulo para la memoria ROM
module testbench();

reg [11:0]address; // Dirección de almacenamiento
wire [7:0]D;// Variable de 7 bits para el módulo

//Llamar al módulo
Mrom A1(address, D);

initial begin
#1
$display("\n");
$display(" Memoria ROM ");
$display("\n");
$display("|----------------|------------|");
$display("|    address     |    Dato    |");
$display("|----------------|------------|");
$monitor("|  %b  |  %b  |", address, D);

// Se declaran las 10 diferentes direcciones
address = 12'b000000000000;
  #1 address = 12'b000000000001;
  #1 address = 12'b000000000010;
  #1 address = 12'b000000000011;
  #1 address = 12'b000000000100;
  #1 address = 12'b000000000101;
  #1 address = 12'b000000000110;
  #1 address = 12'b000000000111;
  #1 address = 12'b000000001000;
  #1 address = 12'b000000001001;
  #1 address = 12'b000000001010;
  end

initial
#200 $finish;

//GTKwave
initial begin
  $dumpfile("Memoria_rom_tb.vcd");
  $dumpvars(0, testbench);
end
endmodule

Laboratorio_8/Memoria_rom/Memoria_rom_tb.vcd
$date
	Sat Oct 24 02:14:13 2020
$end
$version
	Icarus Verilog
$end
$timescale
	1ps
$end
$scope module testbench $end
$var wire 8 ! D [7:0] $end
$var reg 12 " address [11:0] $end
$scope module A1 $end
$var wire 8 # D [7:0] $end
$var wire 12 $ address [11:0] $end
$upscope $end
$upscope $end
$enddefinitions $end
#0
$dumpvars
bx $
bx #
bx "
bx !
$end
#1
b0 !
b0 #
b0 "
b0 $
#2
b11110000 !
b11110000 #
b1 "
b1 $
#3
b111010 !
b111010 #
b10 "
b10 $
#4
b11101100 !
b11101100 #
b11 "
b11 $
#5
b1100000 !
b1100000 #
b100 "
b100 $
#6
b1111000 !
b1111000 #
b101 "
b101 $
#7
b1100110 !
b1100110 #
b110 "
b110 $
#8
b11000110 !
b11000110 #
b111 "
b111 $
#9
b101110 !
b101110 #
b1000 "
b1000 $
#10
b11100100 !
b11100100 #
b1001 "
b1001 $
#11
b11100111 !
b11100111 #
b1010 "
b1010 $
