Laboratorio_9/Ejercicio_02/Ejercicio_02.v
// Electrónica digital
// Valerie Valdez 19659

//                             Laboratorio #09
//                              Ejercicio 02


// Flip Flop D 1 bit
module FFD(input wire clk, EN, reset, input wire C, output reg D);
  always @ (posedge clk, posedge reset) begin

// Non-blockinf assigment
    if(reset) // Colocar todos los valores en 0
      D <= 1'b0;

    else if(EN == 1) // Enabled encendido cuenta cuenta cada flanco del reloj
      D <= C;
  end
endmodule

// Módulo flip flop tipo T
module FFT(input wire clk, EN, reset, output D);
    wire w;
    assign w = ~D;

    FFD A1(clk, EN, reset, w, D);
endmodule

Laboratorio_9/Ejercicio_02/Ejercicio_02_tb.v
// Electrónica digital
// Valerie Valdez 19659

//                             Laboratorio #09
//                              Ejercicio 02

//Testbench

module testbench();

  reg clk, EN, reset;
  wire Q;

// Clock
  always
    #1 clk = ~clk;

// Llamar al módulo del FF tipo T
  FFT B1(clk, EN, reset, Q);

// Inicializar la Prueba
  initial begin
  #1
  $display("\n");
  $display(" Flip Flop tipo T de 1 bit ");
  $display("\n");
  $display("---------------|-----|");
  $display(" clk  EN  reset |  Q  |");
  $display("---------------|-----|");
  $monitor("%b    %b    %b    |  %b  |", clk, EN, reset, Q);

  #1 clk = 0; reset = 1; EN = 0;
  #5 reset = 0; EN = 1;
  #5 reset = 0; EN = 1;
  #5 EN = 0;

  end

  initial
    #20 $finish;

// GTKwave para el diagrama de timing
  initial begin
    $dumpfile("Ejercicio_02_tb.vcd");
    $dumpvars(0, testbench);
  end
endmodule

Laboratorio_9/Ejercicio_02/Ejercicio_02_tb.vcd
$date
	Fri Oct 30 22:53:26 2020
$end
$version
	Icarus Verilog
$end
$timescale
	1ps
$end
$scope module testbench $end
$var wire 1 ! Q $end
$var reg 1 " EN $end
$var reg 1 # clk $end
$var reg 1 $ reset $end
$scope module B1 $end
$var wire 1 " EN $end
$var wire 1 # clk $end
$var wire 1 $ reset $end
$var wire 1 % w $end
$var wire 1 ! D $end
$scope module A1 $end
$var wire 1 % C $end
$var wire 1 " EN $end
$var wire 1 # clk $end
$var wire 1 $ reset $end
$var reg 1 ! D $end
$upscope $end
$upscope $end
$upscope $end
$enddefinitions $end
#0
$dumpvars
x%
x$
x#
x"
x!
$end
#2
1%
0!
0"
1$
0#
#3
1#
#4
0#
#5
1#
#6
0#
#7
0%
1!
1#
1"
0$
#8
0#
#9
1%
0!
1#
#10
0#
#11
0%
1!
1#
#12
0#
#13
1%
0!
1#
#14
0#
#15
0%
1!
1#
#16
0#
#17
1#
0"
