Laboratorio_6/Lab06.v
// Universidad del Valle de Guatemala
// Valerie Valdez (19659)
// Electrónica digital

// ------------------------- Laboratorio No. 6 --------------------------------


// Ejercicio 05
// Flip Flop tipo D de 4 bits con reset síncrono y asíncrono

module FFD(input wire clk, reset, set, input wire [3:0]C, output reg[3:0]D);

// Con always una sección del código estará siempre activado
  always @ (posedge clk, posedge set, posedge reset) begin // Count on the rising edge of the clk

    if(reset) begin  // En caso de reset colocar todas las salidas en 0
      D <= 4'b0;
    end

    else if (set) begin  // En caso de set colocar todas las salidas en 1
      D <= 4'b1111;
    end

    else  // De lo contrario la salida será igual a la entrada
      D <= C;
    end
endmodule



// Ejercicio 06

// Flip Flop tipo D de 2 bits

module FFD2(input wire clk, reset, input wire C, output reg D);
  always @ (posedge clk, posedge reset) begin
    if (reset) begin
      D <= 1'b0;
    end

    else
      D <= C;
    end
endmodule



// Máquina de estados finitos Ejercicio 1

module MF(input wire A, B, clk, reset, output wire Y);
wire S1, S0, S11, S00;

// Ecuaciones booleanas de transiciones
  assign S11 = (S0 & B) | (S1 & A & B);
  assign S00 = (~S1 & ~S0 & A);
  assign Y = (S1 & A & B);

// Utilizar el Flip FLop de 2 bits
  FFD2 U(clk, reset, S11, S1);
  FFD2 U1(clk, reset, S00, S0);


endmodule


// Máquina de estados finitos Ejercicio 3

module MF1(input wire P, clk, reset, output wire Y0, Y1, Y2);
wire S2, S1, S0, S22, S11, S00;

// Ecuaciones booleanas de transiciones
  assign S22 = (~S2 & S1 & S0 & P) | (~S2 & ~S1 & ~S0 & ~P) | (S2 & ~S1 & S0) | (S2 & ~S0 & P) | (S2 & S1 & ~P);
  assign S11 = (~S1 & S0 & P) | (S1 & ~S0 & P) | (S1 & S0 & ~P) | (~S1 & ~S0 & ~P);
  assign S00 = ~S0;

// Utilizar el Flip FLop de 2 bits
  FFD2 U2(clk, reset, S00, S0);
  FFD2 U3(clk, reset, S11, S1);
  FFD2 U4(clk, reset, S22, S2);

// Ecuaciones para las salidas
  assign Y2 = S2;
  assign Y1 = (~S2 & S1) | (S2 & ~S1);
  assign Y0 = (~S1 & S0) | (S1 & ~S0);

endmodule

Laboratorio_6/Lab06_tb.v
// Universidad del Valle de Guatemala
// Valerie Valdez (19659)
// Electrónica digital

// ------------------------- Laboratorio No. 6 --------------------------------

// Testbench

module Testbench();
  reg clk, reset, reset1, set;
  reg [3:0]C;
  reg A, B, P;
  wire S0, S1, S2, S00, S11, S22;
  wire [3:0]D;
  wire Y;
  wire Y0, Y1, Y2;

// Reloj de una unidad de tiempo con cambio en el flanco
always
  begin
    clk <= 1; #1 clk <= ~clk; #1;
end

FFD U(clk, reset, set, C, D);
MF U1(A, B, clk, reset, Y);
MF1 U2(P, clk, reset1, Y0, Y1, Y2);

// Prueba para el Flip Flop tipo D de 4 bits
initial begin
  #1
  $display("\n");
  $display(" FLIP FLOP D de 4 bits ");
  $display("\n");
  $display("C1  R  S  C  | D");
  $display("------------|---");
  $monitor("%b %b %b %b  | %b", clk, reset, set, C, D[3:0]);

    set = 1;

  #5 C[0] = 0; C[1] = 0; C[2] = 0; C[3] = 0; set = 0; reset = 1;
  #5 C[0] = 0; C[1] = 0; C[2] = 1; C[3] = 0; reset = 0;
  #5 C[0] = 0; C[1] = 1; C[2] = 0; C[3] = 1; reset = 0;
  #5 C[0] = 0; C[1] = 0; C[2] = 1; C[3] = 1; reset = 0;

end


initial begin
  #25
  $display("\n");
  $display("Maquina de estados finitos Ej01");
  $display("\n");
  $display(" A B | Y");
  $display("-----|---");
  $monitor("%b %b | %b ", A, B, Y);

      A = 0; B = 0;
   #2 A = 1; B = 0;
   #2 A = 1; B = 1;
   #2 A = 1; B = 1;
   #2 A = 1; B = 1;
   #2 A = 0; B = 0;
   #2 A = 1; B = 0;
   #2 A = 0; B = 0;

 end

initial begin
  #40
      reset1 = 1;
  #1  reset1 = 0;
  $display("\n");
  $display(" Maquina de estados finitos Ej03");
  $display("\n");
  $display("P | Y0 Y1 Y2");
  $display("--|---------");
  $monitor("%b | %b %b %b ", P, Y0, Y1, Y2);
      P = 1;
   #2 P = 1;
   #2 P = 1;
   #2 P = 1;
   #2 P = 0;
   #2 P = 1;
   #2 P = 1;
   #2 P = 1;
   #2 P = 1;
   #2 P = 1;
   #2 P = 1;
   #2 P = 0;
   #2 P = 0;
   #2 P = 0;
   #2 P = 0;

  end

  initial
    #70 $finish;

// GTK wave
  initial begin
    $dumpfile("Lab06_tb.vcd");
    $dumpvars(0, Testbench);
  end
endmodule

Laboratorio_6/Lab06_tb.vcd
$date
	Sun Sep 20 21:38:34 2020
$end
$version
	Icarus Verilog
$end
$timescale
	1ps
$end
$scope module Testbench $end
$var wire 1 ! Y2 $end
$var wire 1 " Y1 $end
$var wire 1 # Y0 $end
$var wire 1 $ Y $end
$var wire 4 % D [3:0] $end
$var reg 1 & A $end
$var reg 1 ' B $end
$var reg 4 ( C [3:0] $end
$var reg 1 ) P $end
$var reg 1 * clk $end
$var reg 1 + reset $end
$var reg 1 , reset1 $end
$var reg 1 - set $end
$scope module U $end
$var wire 4 . C [3:0] $end
$var wire 1 * clk $end
$var wire 1 + reset $end
$var wire 1 - set $end
$var reg 4 / D [3:0] $end
$upscope $end
$scope module U1 $end
$var wire 1 & A $end
$var wire 1 ' B $end
$var wire 1 0 S00 $end
$var wire 1 1 S11 $end
$var wire 1 $ Y $end
$var wire 1 * clk $end
$var wire 1 + reset $end
$var wire 1 2 S1 $end
$var wire 1 3 S0 $end
$scope module U $end
$var wire 1 1 C $end
$var wire 1 * clk $end
$var wire 1 + reset $end
$var reg 1 2 D $end
$upscope $end
$scope module U1 $end
$var wire 1 0 C $end
$var wire 1 * clk $end
$var wire 1 + reset $end
$var reg 1 3 D $end
$upscope $end
$upscope $end
$scope module U2 $end
$var wire 1 ) P $end
$var wire 1 4 S00 $end
$var wire 1 5 S11 $end
$var wire 1 6 S22 $end
$var wire 1 # Y0 $end
$var wire 1 " Y1 $end
$var wire 1 ! Y2 $end
$var wire 1 * clk $end
$var wire 1 , reset $end
$var wire 1 7 S2 $end
$var wire 1 8 S1 $end
$var wire 1 9 S0 $end
$scope module U2 $end
$var wire 1 4 C $end
$var wire 1 * clk $end
$var wire 1 , reset $end
$var reg 1 9 D $end
$upscope $end
$scope module U3 $end
$var wire 1 5 C $end
$var wire 1 * clk $end
$var wire 1 , reset $end
$var reg 1 8 D $end
$upscope $end
$scope module U4 $end
$var wire 1 6 C $end
$var wire 1 * clk $end
$var wire 1 , reset $end
$var reg 1 7 D $end
$upscope $end
$upscope $end
$upscope $end
$enddefinitions $end
#0
$dumpvars
x9
x8
x7
x6
x5
x4
x3
x2
x1
x0
bx /
bx .
x-
x,
x+
1*
x)
bx (
x'
x&
bx %
x$
x#
x"
x!
$end
#1
b1111 %
b1111 /
0*
1-
#2
1*
#3
0*
#4
1*
#5
0*
#6
01
0$
b0 %
b0 /
03
02
1*
1+
0-
b0 (
b0 .
#7
0*
#8
1*
#9
0*
#10
1*
#11
0*
0+
b100 (
b100 .
#12
x1
b100 %
b100 /
x3
1*
#13
0*
#14
x$
x2
1*
#15
0*
#16
b1010 %
b1010 /
1*
b1010 (
b1010 .
#17
0*
#18
1*
#19
0*
#20
1*
#21
0*
b1100 (
b1100 .
#22
b1100 %
b1100 /
1*
#23
0*
#24
1*
#25
0*
01
0$
00
0'
0&
#26
02
03
1*
#27
0*
10
1&
#28
00
13
1*
#29
0*
11
1'
#30
1$
11
12
03
1*
#31
0*
#32
1*
#33
0*
#34
1*
#35
0*
01
0$
0'
0&
#36
02
1*
#37
0*
10
1&
#38
00
13
1*
#39
0*
0&
#40
03
0#
0"
14
09
08
0!
07
1*
1,
#41
0*
06
05
1)
0,
#42
15
1#
04
19
1*
#43
0*
#44
1"
14
18
09
1*
#45
0*
#46
05
16
0#
04
19
1*
#47
0*
#48
14
1!
17
08
09
1*
#49
0*
06
15
0)
#50
0#
04
19
18
0!
07
1*
#51
0*
16
05
1)
#52
14
1!
17
08
09
1*
#53
0*
#54
15
1#
04
19
1*
#55
0*
#56
16
0"
14
18
09
1*
#57
0*
#58
05
06
0#
04
19
1*
#59
0*
#60
14
0!
07
08
09
1*
#61
0*
#62
15
1#
04
19
1*
#63
0*
05
0)
#64
16
15
0#
14
09
1*
#65
0*
#66
0#
0"
04
19
18
1!
17
1*
#67
0*
#68
05
1#
14
09
1*
#69
0*
#70
1"
16
04
19
08
1*
