Laboratorio_8/Alu/alu.v
// Universidad del Valle de Guatemala
// Valerie Valdez

//                         Electrónica digital
//                            Laboratorio 8


// Módulo del la ALU
module ALU(input wire [3:0]D, Q,
            input wire [2:0]S,
            output reg [3:0]Y);

    always @ (D, Q, S) begin
      case (S)
        3'b000: Y <= D & Q ; // Función: A AND B
        3'b001: Y <= D | Q ; // Función: A OR B
        3'b010: Y <= D + Q ; // Función: A ADD B

        3'b011: Y <= Y ; // Colocar el valor pervio

        3'b100: Y <= D & (~Q) ; // Función A AND ~B
        3'b101: Y <= D | (~Q) ; // Función A OR ~B
        3'b110: Y <= D - Q ; // Función A LESS B
        3'b111: Y <= (D < Q) ? 1:0 ; // Función STL. (Comparación entre A y B, por lo que si A > B = 0000, si A < B = 0001)

      default: Y <= 4'b0000 ;// Todo en 0
    endcase
  end
endmodule

Laboratorio_8/Alu/alu_tb.v
// Universidad del Valle de Guatemala
// Valerie Valdez

//                         Electrónica digital
//                            Laboratorio 8

//Módulo
module testbench();

  reg [3:0]D, Q; // Input de la ALU
  reg [2:0]S; // Variable de selección
  wire [3:0]Y;// Salida de 4 bits

// Llamar al módulo
  ALU A3(D, Q, S, Y);

// Inicializar el módulo
  initial begin
  #30
  $display("\n");
  $display("  A L U  ");
  $display("\n");
  $display("|----------------|------|");
  $display("|  D    Q     S  |  Y   |");
  $display("|----------------|------|");
  $monitor("|%b  %b  %b | %b |", D, Q, S, Y);

// Funciones a realizar
  D = 4'b1010; Q = 4'b0011; S = 3'b000; //FUNCION  A AND B
  #1 S = 3'b001; // Función A OR B
  #1 S = 3'b010; // Función A ADD B
  #1 S = 3'b010; // Función A ADD B

  #1 S = 3'b011; //Colocar el valor previo

  #1 S = 3'b100; // Función A AND ~B
  #1 S = 3'b101; // Función A OR ~B
  #1 S = 3'b110; // Función A LESS B
  #1 S = 3'b111; // Función STL
  #1 D = 4'b010; Q = 4'b0011; // Colocar todo en 0

  #2 $finish;
  end

//GTKwave
  initial begin
        $dumpfile("alu_tb.vcd");
        $dumpvars(0, testbench);
      end

endmodule

Laboratorio_8/Alu/alu_tb.vcd
$date
	Sat Oct 24 03:17:40 2020
$end
$version
	Icarus Verilog
$end
$timescale
	1ps
$end
$scope module testbench $end
$var wire 4 ! Y [3:0] $end
$var reg 4 " D [3:0] $end
$var reg 4 # Q [3:0] $end
$var reg 3 $ S [2:0] $end
$scope module A3 $end
$var wire 4 % D [3:0] $end
$var wire 4 & Q [3:0] $end
$var wire 3 ' S [2:0] $end
$var reg 4 ( Y [3:0] $end
$upscope $end
$upscope $end
$enddefinitions $end
#0
$dumpvars
bx (
bx '
bx &
bx %
bx $
bx #
bx "
bx !
$end
#30
b10 !
b10 (
b0 $
b0 '
b11 #
b11 &
b1010 "
b1010 %
#31
b1011 !
b1011 (
b1 $
b1 '
#32
b1101 !
b1101 (
b10 $
b10 '
#34
b11 $
b11 '
#35
b1000 !
b1000 (
b100 $
b100 '
#36
b1110 !
b1110 (
b101 $
b101 '
#37
b111 !
b111 (
b110 $
b110 '
#38
b0 !
b0 (
b111 $
b111 '
#39
b1 !
b1 (
b10 "
b10 %
