Laboratorio_3/01_TABLA_SOP/01_TABLA_SOP.v
// Electrónica digital, Laboratorio 3

// ---------- Valerie Valdez 19659 ----------
// Programación de la tabla SOP número uno.

module TABLA_SOP(); // Nombre del módulo

// Declaración de variables

reg A, B, C;
wire out0,out1,out2,out3,out4,out5,out6,out7,out8;


// Declaración de compuertas

not nai(out0, A);
not naiI(out1, B);
not naiII(out2, C);
and soshite(out3, out0,out1,out2);
and soshiteI(out4, out0,B,out2);
and soshiteII(out5, A,out1,out2);
and soshiteII(out6, A,out1,C);
and soshiteIV(out7, A,B,C);
or matawa(out8, out3,out4,out5,out6,out7);


// Establecer eventos a través del tiempo

initial begin
  $display("A B C | Y");
  $display("----------");
  $monitor("%b %b %b | %b",A, B, C, out8);


// Declaración de los valores en t = 0

  A = 0;
  B = 0;
  C = 0;


// Declaración de los valores en el tiempo restante

  #1 C = 1;
  #1 B = 1; C = 0;
  #1 C = 1;
  #1 A = 1; B = 0; C = 0;
  #1 C = 1;
  #1 B = 1; C = 0;
  #1 C = 1;
  #1 $finish;
end


  initial
    begin
      $dumpfile("01_TABLA_SOP_tb.vcd");
      $dumpvars(0, TABLA_SOP);
    end
endmodule

01_TABLA_SOP/01_TABLA_SOP_tb.vcd
$date
	Sun Aug 02 15:46:21 2020
$end
$version
	Icarus Verilog
$end
$timescale
	1ps
$end
$scope module TABLA_SOP $end
$var wire 1 ! out0 $end
$var wire 1 " out1 $end
$var wire 1 # out2 $end
$var wire 1 $ out3 $end
$var wire 1 % out4 $end
$var wire 1 & out5 $end
$var wire 1 ' out6 $end
$var wire 1 ( out7 $end
$var wire 1 ) out8 $end
$var reg 1 * A $end
$var reg 1 + B $end
$var reg 1 , C $end
$upscope $end
$enddefinitions $end
#0
$dumpvars
0,
0+
0*
1)
0(
0'
0&
0%
1$
1#
1"
1!
$end
#1
0)
0$
0#
1,
#2
1)
1%
1#
0"
0,
1+
#3
0)
0%
0#
1,
#4
1)
1&
1#
1"
0!
0,
0+
1*
#5
0&
1'
0#
1,
#6
0)
0'
1#
0"
0,
1+
#7
1)
1(
0#
1,
